{"type": "FeatureCollection", "features": [{"type": "Feature", "bbox": [-122.3582706802915, 47.6234354197085, -122.3555727197085, 47.6261333802915], "properties": {"Average Score": 28.6, "High Score": 90, "Address": "601 Queen Anne Ave N, Seattle, WA 98109, USA", "Total Inspections": 5, "Business Name": "TOULOUSE PETIT KITCHEN & LOUNGE"}, "geometry": {"type": "Point", "coordinates": [-122.3569217, 47.6247844]}}, {"type": "Feature", "bbox": [-122.3575091802915, 47.6230362197085, -122.3548112197085, 47.6257341802915], "properties": {"Average Score": 27.5, "High Score": 80, "Address": "11 Mercer St, Seattle, WA 98109, USA", "Total Inspections": 4, "Business Name": "OBASAN"}, "geometry": {"type": "Point", "coordinates": [-122.3561602, 47.6243852]}}, {"type": "Feature", "bbox": [-122.3561488802915, 47.6233912197085, -122.3534509197085, 47.6260891802915], "properties": {"Average Score": 17.5, "High Score": 70, "Address": "100 Mercer St, Seattle, WA 98109, USA", "Total Inspections": 4, "Business Name": "AFC SUSHI @ METOPOLITAN MARKET#157"}, "geometry": {"type": "Point", "coordinates": [-122.3547999, 47.6247402]}}, {"type": "Feature", "bbox": [-122.3406733302915, 47.6250295197085, -122.3379753697085, 47.62772748029149], "properties": {"Average Score": 32.25, "High Score": 70, "Address": "731 Westlake Ave N, Seattle, WA 98109, USA", "Total Inspections": 4, "Business Name": "ART MARBLE 21"}, "geometry": {"type": "Point", "coordinates": [-122.3393243, 47.6263785]}}, {"type": "Feature", "bbox": [-122.3571007802915, 47.6180883197085, -122.3544028197085, 47.6207862802915], "properties": {"Average Score": 25.0, "High Score": 68, "Address": "129 1st Ave N, Seattle, WA 98109, USA", "Total Inspections": 4, "Business Name": "PLAZA GARIBALDI, INC."}, "geometry": {"type": "Point", "coordinates": [-122.3557518, 47.6194373]}}, {"type": "Feature", "bbox": [-122.3585318802915, 47.6365129197085, -122.3558339197085, 47.63921088029149], "properties": {"Average Score": 24.25, "High Score": 67, "Address": "2121 Queen Anne Ave N, Seattle, WA 98109, USA", "Total Inspections": 4, "Business Name": "QUEEN ANNE CAFE"}, "geometry": {"type": "Point", "coordinates": [-122.3571829, 47.6378619]}}, {"type": "Feature", "bbox": [-122.3393069802915, 47.6220631197085, -122.3366090197085, 47.6247610802915], "properties": {"Average Score": 15.333333333333334, "High Score": 66, "Address": "920 Republican St, Seattle, WA 98109, USA", "Total Inspections": 6, "Business Name": "BLUE MOON BURGERS"}, "geometry": {"type": "Point", "coordinates": [-122.337958, 47.6234121]}}, {"type": "Feature", "bbox": [-122.3565861802915, 47.6224726197085, -122.3538882197085, 47.6251705802915], "properties": {"Average Score": 29.0, "High Score": 65, "Address": "516 1st Ave N, Seattle, WA 98109, USA", "Total Inspections": 5, "Business Name": "SAFEWAY #1885- CHINA DELI / BAKERY"}, "geometry": {"type": "Point", "coordinates": [-122.3552372, 47.6238216]}}, {"type": "Feature", "bbox": [-122.3583413802915, 47.6235408197085, -122.3556434197085, 47.62623878029149], "properties": {"Average Score": 23.25, "High Score": 62, "Address": "605 Queen Anne Ave N, Seattle, WA 98109, USA", "Total Inspections": 4, "Business Name": "PESO'S"}, "geometry": {"type": "Point", "coordinates": [-122.3569924, 47.6248898]}}, {"type": "Feature", "bbox": [-122.3574952802915, 47.6363732197085, -122.3547973197085, 47.6390711802915], "properties": {"Average Score": 25.5, "High Score": 60, "Address": "2100 Queen Anne Ave N, Seattle, WA 98109, USA", "Total Inspections": 4, "Business Name": "SAFEWAY STORE #368"}, "geometry": {"type": "Point", "coordinates": [-122.3561463, 47.6377222]}}]}